mybasicpy/__init__.py
mybasicpy/functions.py
mybasicpy/greet.py
mybasicpy-0.0.4.dist-info/LICENSE.rst
mybasicpy-0.0.4.dist-info/METADATA
mybasicpy-0.0.4.dist-info/WHEEL
mybasicpy-0.0.4.dist-info/top_level.txt
mybasicpy-0.0.4.dist-info/RECORD
